modlog/__init__.py
modlog/main.py
modlog-0.0.2.dist-info/LICENSE
modlog-0.0.2.dist-info/METADATA
modlog-0.0.2.dist-info/WHEEL
modlog-0.0.2.dist-info/entry_points.txt
modlog-0.0.2.dist-info/top_level.txt
modlog-0.0.2.dist-info/RECORD
